Outlier_Nishant/Outlier_N.py
Outlier_Nishant/__init__.py
Outlier_Nishant/outcli.py
outlierpack_101703375_p2-0.9.dist-info/LICENSE
outlierpack_101703375_p2-0.9.dist-info/METADATA
outlierpack_101703375_p2-0.9.dist-info/WHEEL
outlierpack_101703375_p2-0.9.dist-info/entry_points.txt
outlierpack_101703375_p2-0.9.dist-info/top_level.txt
outlierpack_101703375_p2-0.9.dist-info/RECORD
