Metadata-Version: 2.1
Name: outlierpack-101703375-p2
Version: 0.9
Summary: A small package that removes outlier
Home-page: https://github.com/NishantDhanda/Outlier-Nishant.git
Author: Nishant Dhanda
Author-email: dhandanishant012@gmail.com
License: UNKNOWN
Platform: UNKNOWN
Classifier: Programming Language :: Python :: 3
Classifier: License :: OSI Approved :: MIT License
Classifier: Operating System :: OS Independent
Requires-Python: >=3.6
